README.rst
setup.py
lib/spark-examples-1.6.0.jar
pyspark_hbase.egg-info/PKG-INFO
pyspark_hbase.egg-info/SOURCES.txt
pyspark_hbase.egg-info/dependency_links.txt
pyspark_hbase.egg-info/requires.txt
pyspark_hbase.egg-info/top_level.txt
shbase/__init__.py
shbase/config.py
shbase/shb.py
shbase/utils.py