Metadata-Version: 1.1
Name: pyspark-hbase
Version: 0.0.4
Summary: pyspark hbase hadoop utils
Home-page: https://github.com/songjian28/pyspark-hbase
Author: SONG JIAN
Author-email: songjian9228@163.com
License: MIT
Keywords: spark hbase
Platform: UNKNOWN
Classifier: Development Status :: 3 - Alpha
Classifier: Intended Audience :: Developers
Classifier: Topic :: Software Development :: Build Tools
Classifier: License :: OSI Approved :: MIT License
Classifier: Programming Language :: Python
Classifier: Programming Language :: Python :: 2
Classifier: Programming Language :: Python :: 2.6
Classifier: Programming Language :: Python :: 2.7
